htschema/__init__.py
htschema/validate.py
htschema-0.1.0.dist-info/METADATA
htschema-0.1.0.dist-info/WHEEL
htschema-0.1.0.dist-info/entry_points.txt
htschema-0.1.0.dist-info/RECORD
