Metadata-Version: 2.1
Name: htschema
Version: 0.1.0
Summary: 
Author: Mark Baggett
Author-email: markpbaggett@gmail.com
Requires-Python: >=3.12,<4.0
Classifier: Programming Language :: Python :: 3
Classifier: Programming Language :: Python :: 3.12
Requires-Dist: click (>=8.1.7,<9.0.0)
Requires-Dist: jsonschema (>=4.23.0,<5.0.0)
Requires-Dist: yamllint (>=1.35.1,<2.0.0)
